b_cfn_custom_api_key_authorizer/__init__.py
b_cfn_custom_api_key_authorizer/api_keys_database.py
b_cfn_custom_api_key_authorizer/authorization_type.py
b_cfn_custom_api_key_authorizer/custom_authorizer.py
b_cfn_custom_api_key_authorizer/functions/__init__.py
b_cfn_custom_api_key_authorizer/functions/base_function.py
b_cfn_custom_api_key_authorizer/functions/authorizer/__init__.py
b_cfn_custom_api_key_authorizer/functions/authorizer/function.py
b_cfn_custom_api_key_authorizer/functions/authorizer/source/__init__.py
b_cfn_custom_api_key_authorizer/functions/authorizer/source/index.py
b_cfn_custom_api_key_authorizer/functions/authorizer/source/policy_document.py
b_cfn_custom_api_key_authorizer/functions/deleter/__init__.py
b_cfn_custom_api_key_authorizer/functions/deleter/function.py
b_cfn_custom_api_key_authorizer/functions/deleter/source/__init__.py
b_cfn_custom_api_key_authorizer/functions/deleter/source/index.py
b_cfn_custom_api_key_authorizer/functions/exists/__init__.py
b_cfn_custom_api_key_authorizer/functions/exists/function.py
b_cfn_custom_api_key_authorizer/functions/exists/source/__init__.py
b_cfn_custom_api_key_authorizer/functions/exists/source/index.py
b_cfn_custom_api_key_authorizer/functions/generator/__init__.py
b_cfn_custom_api_key_authorizer/functions/generator/function.py
b_cfn_custom_api_key_authorizer/functions/generator/source/__init__.py
b_cfn_custom_api_key_authorizer/functions/generator/source/index.py
b_cfn_custom_api_key_authorizer/functions/validator/__init__.py
b_cfn_custom_api_key_authorizer/functions/validator/function.py
b_cfn_custom_api_key_authorizer/functions/validator/source/__init__.py
b_cfn_custom_api_key_authorizer/functions/validator/source/index.py
b_cfn_custom_api_key_authorizer_layer/__init__.py
b_cfn_custom_api_key_authorizer_layer/authorizer_layer.py
b_cfn_custom_api_key_authorizer_layer/source/__init__.py
b_cfn_custom_api_key_authorizer_layer/source/python/__init__.py
b_cfn_custom_api_key_authorizer-3.0.0.dist-info/LICENSE
b_cfn_custom_api_key_authorizer-3.0.0.dist-info/METADATA
b_cfn_custom_api_key_authorizer-3.0.0.dist-info/WHEEL
b_cfn_custom_api_key_authorizer-3.0.0.dist-info/top_level.txt
b_cfn_custom_api_key_authorizer-3.0.0.dist-info/RECORD
