Metadata-Version: 2.1
Name: b-cfn-custom-api-key-authorizer
Version: 3.0.0
Summary: Enables ApiKey functionality (like in ApiGateway V1) for ApiGateway V2.
Home-page: https://github.com/biomapas/B.CfnCustomApiKeyAuthorizer.git
License: Apache License 2.0
Keywords: AWS Cognito api_key Authorizer
Classifier: Programming Language :: Python :: 3
Classifier: Operating System :: OS Independent
License-File: LICENSE
Requires-Dist: aws-cdk-lib (<3.0.0,>=2.0.0)
Requires-Dist: aws-cdk-constructs (<3.0.0,>=2.0.0)
